bink/__init__.py
bink/choices.py
bink/story.py
bink/tags.py
bink/native/arm64/libbink.dylib
bink/native/arm64/libbink.so
bink/native/x86_64/bink.dll
bink/native/x86_64/libbink.so
bink-0.5.0.dist-info/licenses/LICENSE
bink-0.5.0.dist-info/METADATA
bink-0.5.0.dist-info/WHEEL
bink-0.5.0.dist-info/top_level.txt
bink-0.5.0.dist-info/RECORD
