Metadata-Version: 2.4
Name: bink
Version: 0.5.0
Summary: Runtime for Ink, a scripting language for writing interactive narrative
Author: Rafael Garcia
License: Apache 2.0
Classifier: Programming Language :: Python :: 3
License-File: LICENSE
Dynamic: license-file
